send_sms_freemobile/__init__.py
send_sms_freemobile/application.py
send_sms_freemobile/client.py
send_sms_freemobile-0.1.0.dist-info/entry_points.txt
send_sms_freemobile-0.1.0.dist-info/WHEEL
send_sms_freemobile-0.1.0.dist-info/METADATA
send_sms_freemobile-0.1.0.dist-info/RECORD
